hgru_cuda.cpython-36m-x86_64-linux-gnu.so
hgru_real_cuda.cpython-36m-x86_64-linux-gnu.so
hgru/__init__.py
hgru/bihgru1d.py
hgru/bihgru2d.py
hgru/hgru1d.py
hgru/hgru2d.py
hgru/hgrureal1d.py
hgru/hgrureal2d.py
hgru/helpers/__init__.py
hgru/helpers/helpers.py
hgru/hgru_cuda/__init__.py
hgru/hgru_cuda/hgru_function.py
hgru/hgru_real_cuda/__init__.py
hgru/hgru_real_cuda/hgru_real_function.py
hgru-0.0.0.dist-info/METADATA
hgru-0.0.0.dist-info/WHEEL
hgru-0.0.0.dist-info/top_level.txt
hgru-0.0.0.dist-info/RECORD
