Metadata-Version: 2.1
Name: hgru
Version: 0.0.0
Summary: UNKNOWN
Home-page: https://github.com/Doraemonzzz/hgru-pytorch
License: UNKNOWN
Keywords: artificial intelligence,sequential model
Platform: UNKNOWN
Classifier: Development Status :: 3 - Alpha
Classifier: Intended Audience :: Developers
Classifier: Topic :: Scientific/Engineering :: Artificial Intelligence
Classifier: License :: OSI Approved :: MIT License
Classifier: Programming Language :: Python :: 3.6
Requires-Dist: torch
Requires-Dist: einops
